Metadata-Version: 1.1
Name: jupyter-nim-kernel
Version: 1.3
Summary: Simple Nim kernel for Jupyter
Home-page: https://github.com/stisa/jupyter-nim-kernel.git
Author: stisa
Author-email: silvio@stisa.space
License: UNKNOWN
Download-URL: https://github.com/stisa/jupyter-nim-kernel/archive/master.zip
Keywords: jupyter,kernel,nim
Platform: UNKNOWN
